RecordMapper/RecordMapper.py
RecordMapper/__init__.py
RecordMapper/appliers/CleanApplier.py
RecordMapper/appliers/NestedSchemaSelectorApplier.py
RecordMapper/appliers/RenameApplier.py
RecordMapper/appliers/TransformApplier.py
RecordMapper/appliers/__init__.py
RecordMapper/avro/AvroReader.py
RecordMapper/avro/AvroWriter.py
RecordMapper/avro/__init__.py
RecordMapper/builders/BuiltinFunctions.py
RecordMapper/builders/FlatRecordBuilder.py
RecordMapper/builders/FlatSchemaBuilder.py
RecordMapper/builders/FunctionBuilder.py
RecordMapper/builders/__init__.py
RecordMapper/common/Reader.py
RecordMapper/common/Writer.py
RecordMapper/common/__init__.py
RecordMapper/csv/CSVReader.py
RecordMapper/csv/CSVWriter.py
RecordMapper/csv/__init__.py
RecordMapper/utils.py
RecordMapper/xml/XMLReader.py
RecordMapper/xml/__init__.py
recordmapper-0.7.dist-info/LICENSE
recordmapper-0.7.dist-info/WHEEL
recordmapper-0.7.dist-info/METADATA
recordmapper-0.7.dist-info/RECORD
